restmachine_aws/__init__.py
restmachine_aws/__main__.py
restmachine_aws/_version.py
restmachine_aws/adapter.py
restmachine_aws/extension.py
restmachine_aws/metrics.py
restmachine_aws-0.1.1.dist-info/METADATA
restmachine_aws-0.1.1.dist-info/WHEEL
restmachine_aws-0.1.1.dist-info/top_level.txt
restmachine_aws-0.1.1.dist-info/RECORD
